engineering_notation/__init__.py
engineering_notation/eng_notation.py
engineering_notation/version.py
engineering_notation-0.12.0.dist-info/METADATA
engineering_notation-0.12.0.dist-info/WHEEL
engineering_notation-0.12.0.dist-info/top_level.txt
engineering_notation-0.12.0.dist-info/RECORD
