Metadata-Version: 2.4
Name: engineering-notation
Version: 0.12.0
Summary: Easy engineering notation
Requires-Python: >=3.11
